fe_exam_samples/__init__.py
fe_exam_samples/python/level1_average.py
fe_exam_samples/python/level1_binary_search.py
fe_exam_samples/python/level1_bubble_sort.py
fe_exam_samples/python/level1_celsius_to_fahrenheit.py
fe_exam_samples/python/level1_count_digits.py
fe_exam_samples/python/level1_countdown.py
fe_exam_samples/python/level1_digit_sum.py
fe_exam_samples/python/level1_even_numbers.py
fe_exam_samples/python/level1_factorial.py
fe_exam_samples/python/level1_fibonacci.py
fe_exam_samples/python/level1_gcd.py
fe_exam_samples/python/level1_hello_name.py
fe_exam_samples/python/level1_insertion_sort.py
fe_exam_samples/python/level1_is_anagram.py
fe_exam_samples/python/level1_lcm.py
fe_exam_samples/python/level1_linear_search.py
fe_exam_samples/python/level1_list_sum.py
fe_exam_samples/python/level1_max_of_two.py
fe_exam_samples/python/level1_min_of_list.py
fe_exam_samples/python/level1_multiplication_table.py
fe_exam_samples/python/level1_palindrome.py
fe_exam_samples/python/level1_prime_check.py
fe_exam_samples/python/level1_reverse_string.py
fe_exam_samples/python/level1_second_largest.py
fe_exam_samples/python/level1_selection_sort.py
fe_exam_samples/python/level1_sign_checker.py
fe_exam_samples/python/level1_string_length.py
fe_exam_samples/python/level1_sum_to_n.py
fe_exam_samples/python/level1_unique_characters.py
fe_exam_samples/python/level1_unique_elements.py
fe_exam_samples/python/level1_vowel_count.py
fe_exam_samples/python/level2_binary_search_bounds.py
fe_exam_samples/python/level2_bracket_validation.py
fe_exam_samples/python/level2_fe_r01_autumn_inventory_forecast.py
fe_exam_samples/python/level2_fe_r01_spring_text_statistics.py
fe_exam_samples/python/level2_fe_r02_autumn_packet_scheduler.py
fe_exam_samples/python/level2_fe_r02_spring_task_dependency.py
fe_exam_samples/python/level2_greedy_coin_change.py
fe_exam_samples/python/level2_group_anagrams.py
fe_exam_samples/python/level2_interval_merge.py
fe_exam_samples/python/level2_matrix_transpose.py
showtracetable-0.0.1.dist-info/licenses/LICENSE
showtracetable-0.0.1.dist-info/METADATA
showtracetable-0.0.1.dist-info/WHEEL
showtracetable-0.0.1.dist-info/entry_points.txt
showtracetable-0.0.1.dist-info/top_level.txt
showtracetable-0.0.1.dist-info/RECORD
