Metadata-Version: 2.4
Name: showtracetable
Version: 0.0.1
Summary: Console tracer that renders simple call-traces of Python programs as ASCII diagrams
Author: hayashikunita
License-Expression: MIT
Project-URL: Homepage, https://github.com/hayashikunita/showtracetable
Project-URL: Repository, https://github.com/hayashikunita/showtracetable
Project-URL: Issues, https://github.com/hayashikunita/showtracetable/issues
Keywords: trace,tracer,debug,education,teaching,csv,python,step,visualization
Classifier: Development Status :: 3 - Alpha
Classifier: Intended Audience :: Education
Classifier: Intended Audience :: Developers
Classifier: Programming Language :: Python
Classifier: Programming Language :: Python :: 3
Classifier: Programming Language :: Python :: 3 :: Only
Classifier: Programming Language :: Python :: 3.8
Classifier: Programming Language :: Python :: 3.9
Classifier: Programming Language :: Python :: 3.10
Classifier: Programming Language :: Python :: 3.11
Classifier: Programming Language :: Python :: 3.12
Classifier: Programming Language :: Python :: 3.13
Classifier: Operating System :: OS Independent
Classifier: Topic :: Software Development :: Debuggers
Classifier: Topic :: Education
Requires-Python: >=3.8
License-File: LICENSE
Provides-Extra: test
Requires-Dist: pytest>=7; extra == "test"
Requires-Dist: pytest-cov>=4; extra == "test"
Dynamic: license-file
